diepX/__about__.py
diepX/__init__.py
diepX/__main__.py
diepX/bkg.mp3
diepX/diepX.py
diepX/explosion.ogg
diepX/hit.ogg
diepX/shooting.ogg
diepX/__pycache__/__about__.cpython-38.pyc
diepX/__pycache__/__init__.cpython-38.pyc
diepX/__pycache__/__main__.cpython-38.pyc
diepX/__pycache__/diepX.cpython-38.pyc
diep_X-0.1.0a8.dist-info/LICENSE
diep_X-0.1.0a8.dist-info/METADATA
diep_X-0.1.0a8.dist-info/WHEEL
diep_X-0.1.0a8.dist-info/top_level.txt
diep_X-0.1.0a8.dist-info/RECORD
