Metadata-Version: 2.1
Name: diep-X
Version: 0.1.0a8
Summary: A mini tank-shooting game
Home-page: https://github.com/tank-overlord/diep-X
Author: Tank Overlord
Author-email: TankOverLord88@gmail.com
License: BSD 3-Clause
Platform: UNKNOWN
Classifier: Topic :: Games/Entertainment
Classifier: Programming Language :: Python :: 3
Classifier: Programming Language :: Python :: 3.6
Classifier: Programming Language :: Python :: 3.7
Classifier: Programming Language :: Python :: 3.8
Classifier: License :: OSI Approved :: BSD License
Classifier: Development Status :: 3 - Alpha
Classifier: Operating System :: OS Independent
Requires-Python: >=3.6
Requires-Dist: pygame (>=2.0.0)
